CHANGELOG.txt
LICENSE.txt
MANIFEST.in
README.txt
setup.py
PaymentDTO/CapturePayment.py
PaymentDTO/CardTransactionDetails.py
PaymentDTO/MessageLayer.py
PaymentDTO/Payment.py
PaymentDTO/PaymentResponse.py
PaymentDTO/Product.py
PaymentDTO/RefundPayment.py
PaymentDTO/VoidPayment.py
PaymentDTO/__init__.py
PaymentService/OnlinePayment.py
PaymentService/__init__.py
SamplePayments.egg-info/PKG-INFO
SamplePayments.egg-info/SOURCES.txt
SamplePayments.egg-info/dependency_links.txt
SamplePayments.egg-info/requires.txt
SamplePayments.egg-info/top_level.txt